[
    {
        "title": "Senior Analytics Engineer H/F",
        "entreprise": "PayFit",
        "localisation": "Paris 8e - 75",
        "contrat": "CDI",
        "description": "",
        "link": "https://www.hellowork.com/fr-fr/emplois/60257918.html"
    },
    {
        "title": "Senior Analytics Engineer H/F",
        "entreprise": "Shippeo",
        "localisation": "Paris 10e - 75",
        "contrat": "CDI",
        "description": "",
        "link": "https://www.hellowork.com/fr-fr/emplois/59735948.html"
    },
    {
        "title": "Ingénieur - Ingénieure Big Data Palantir H/F",
        "entreprise": "SIBYL",
        "localisation": "Paris 9e - 75",
        "contrat": "CDI",
        "description": "",
        "link": "https://www.hellowork.com/fr-fr/emplois/61979166.html"
    },
    {
        "title": "Expert Big Data H/F",
        "entreprise": "CGI",
        "localisation": "",
        "contrat": "",
        "description": "",
        "link": "https://www.hellowork.com/fr-fr/emplois/60655692.html"
    },
    {
        "title": "Analytics Engineer H/F",
        "entreprise": "Younited Credit",
        "localisation": "Paris 9e - 75",
        "contrat": "CDI",
        "description": "",
        "link": "https://www.hellowork.com/fr-fr/emplois/60681291.html"
    },
    {
        "title": "Senior Backend Engineer Craftman et Appétence Data Spécialiste en Big Data Paris ou Remote Partiel H/F",
        "entreprise": "Octopus IT",
        "localisation": "",
        "contrat": "",
        "description": "",
        "link": "https://www.hellowork.com/fr-fr/emplois/57414073.html"
    },
    {
        "title": "Date Engineer Python Pandas - SQL Scale Up Medtech Remote Flexible H/F",
        "entreprise": "Octopus IT",
        "localisation": "",
        "contrat": "",
        "description": "",
        "link": "https://www.hellowork.com/fr-fr/emplois/57414253.html"
    },
    {
        "title": "Senior Analytics Engineer H/F",
        "entreprise": "Mirakl",
        "localisation": "Paris - 75",
        "contrat": "CDI",
        "description": "",
        "link": "https://www.hellowork.com/fr-fr/emplois/60609605.html"
    },
    {
        "title": "Mid Analytics Engineer All Genders H/F",
        "entreprise": "Dailymotion",
        "localisation": "Paris - 75",
        "contrat": "CDI",
        "description": "",
        "link": "https://www.hellowork.com/fr-fr/emplois/61723726.html"
    },
    {
        "title": "Senior Analytics Engineer H/F",
        "entreprise": "Mirakl",
        "localisation": "Paris - 75",
        "contrat": "CDI",
        "description": "",
        "link": "https://www.hellowork.com/fr-fr/emplois/60314341.html"
    },
    {
        "title": "Senior Analytics Engineer All Genders H/F",
        "entreprise": "Dailymotion",
        "localisation": "Paris - 75",
        "contrat": "CDI",
        "description": "",
        "link": "https://www.hellowork.com/fr-fr/emplois/61528477.html"
    },
    {
        "title": "Si vous étiez notre Prochain H/F",
        "entreprise": "Compagnie des Alpes",
        "localisation": "Paris 9e - 75",
        "contrat": "CDI",
        "description": "",
        "link": "https://www.hellowork.com/fr-fr/emplois/59197861.html"
    },
    {
        "title": "Ingénieur Big Data H/F",
        "entreprise": "Cgilanum",
        "localisation": "Paris 1er - 75",
        "contrat": "CDI",
        "description": "",
        "link": "https://www.hellowork.com/fr-fr/emplois/61489695.html"
    },
    {
        "title": "Ingénieur Big Data H/F",
        "entreprise": "SOMA",
        "localisation": "",
        "contrat": "",
        "description": "",
        "link": "https://www.hellowork.com/fr-fr/emplois/61278439.html"
    },
    {
        "title": "Analytics Engineer H/F",
        "entreprise": "SOMA",
        "localisation": "",
        "contrat": "",
        "description": "",
        "link": "https://www.hellowork.com/fr-fr/emplois/61277951.html"
    },
    {
        "title": "Saint Laurent Analyst Engineer Intern W - m H/F",
        "entreprise": "Kering",
        "localisation": "Paris - 75",
        "contrat": "CDI",
        "description": "",
        "link": "https://www.hellowork.com/fr-fr/emplois/57721144.html"
    },
    {
        "title": "Lead Analytics Engineer All Genders H/F",
        "entreprise": "Dailymotion",
        "localisation": "Paris - 75",
        "contrat": "CDI",
        "description": "",
        "link": "https://www.hellowork.com/fr-fr/emplois/61211618.html"
    },
    {
        "title": "Data Ops H/F",
        "entreprise": "Bluecoders",
        "localisation": "Paris 11e - 75",
        "contrat": "CDI",
        "description": "",
        "link": "https://www.hellowork.com/fr-fr/emplois/61024639.html"
    },
    {
        "title": "Ingénieur Data Senior 6+ Ans d'Expérience Minimum H/F",
        "entreprise": "IOTA GROUP",
        "localisation": "Paris - 75",
        "contrat": "Indépendant/Freelance",
        "description": "",
        "link": "https://www.hellowork.com/fr-fr/emplois/60936802.html"
    },
    {
        "title": "Développeur Fullstack Javascript Freelance H/F",
        "entreprise": "Kicklox",
        "localisation": "Paris - 75",
        "contrat": "Indépendant/Freelance",
        "description": "",
        "link": "https://www.hellowork.com/fr-fr/emplois/60929193.html"
    }
]